scopes.py
scopes-0.2.0.dist-info/DESCRIPTION.rst
scopes-0.2.0.dist-info/METADATA
scopes-0.2.0.dist-info/RECORD
scopes-0.2.0.dist-info/WHEEL
scopes-0.2.0.dist-info/metadata.json
scopes-0.2.0.dist-info/top_level.txt
