Metadata-Version: 2.0
Name: scopes
Version: 0.2.0
Summary: A container class for authorization scopes
Home-page: https://github.com/te-je/scopes
Author: Te-jé Rodgers
Author-email: tjd.rodgers@gmail.com
License: MIT
Platform: UNKNOWN
Classifier: Development Status :: 3 - Alpha
Classifier: Intended Audience :: Developers
Classifier: License :: OSI Approved :: MIT License
Classifier: Programming Language :: Python :: 3
Classifier: Programming Language :: Python :: 3.2
Classifier: Programming Language :: Python :: 3.3
Classifier: Programming Language :: Python :: 3.4
Classifier: Programming Language :: Python :: 3.5
